odoo/addons/connector_infor/README.rst
odoo/addons/connector_infor/__init__.py
odoo/addons/connector_infor/__manifest__.py
odoo/addons/connector_infor/components/__init__.py
odoo/addons/connector_infor/components/base.py
odoo/addons/connector_infor/components/messager.py
odoo/addons/connector_infor/components/poster.py
odoo/addons/connector_infor/components/producer.py
odoo/addons/connector_infor/components/record_locker.py
odoo/addons/connector_infor/components/storage.py
odoo/addons/connector_infor/data/ir_sequence.xml
odoo/addons/connector_infor/i18n/connector_infor.pot
odoo/addons/connector_infor/i18n/fr.po
odoo/addons/connector_infor/models/__init__.py
odoo/addons/connector_infor/models/frequency_mixin.py
odoo/addons/connector_infor/models/infor_backend.py
odoo/addons/connector_infor/models/infor_binding.py
odoo/addons/connector_infor/models/infor_message.py
odoo/addons/connector_infor/security/connector_security.xml
odoo/addons/connector_infor/security/ir.model.access.csv
odoo/addons/connector_infor/static/description/icon.png
odoo/addons/connector_infor/tests/__init__.py
odoo/addons/connector_infor/tests/common.py
odoo/addons/connector_infor/tests/test_backend.py
odoo/addons/connector_infor/tests/test_infor_message.py
odoo/addons/connector_infor/tests/test_locker.py
odoo/addons/connector_infor/tests/test_producer.py
odoo/addons/connector_infor/tests/examples/in-1.xml
odoo/addons/connector_infor/tests/examples/out-1.xml
odoo/addons/connector_infor/views/connector_infor_menu.xml
odoo/addons/connector_infor/views/infor_backend_views.xml
odoo/addons/connector_infor/views/infor_message_views.xml
odoo11_addon_connector_infor-11.0.1.0.0.99.dev30.dist-info/METADATA
odoo11_addon_connector_infor-11.0.1.0.0.99.dev30.dist-info/RECORD
odoo11_addon_connector_infor-11.0.1.0.0.99.dev30.dist-info/WHEEL
odoo11_addon_connector_infor-11.0.1.0.0.99.dev30.dist-info/top_level.txt
