Metadata-Version: 2.1
Name: odoo11-addon-connector-infor
Version: 11.0.1.0.0.99.dev30
Summary: Integration between Odoo and Infor
Home-page: https://github.com/OCA/connector_infor
Author: Open Source Integrators, Odoo Community Association (OCA)
Author-email: support@odoo-community.org
License: AGPL-3
Platform: UNKNOWN
Classifier: Programming Language :: Python
Classifier: Framework :: Odoo
Classifier: License :: OSI Approved :: GNU Affero General Public License v3
Requires-Python: >=2.7, !=3.0.*, !=3.1.*, !=3.2.*, !=3.3.*, !=3.4.*
Requires-Dist: odoo11-addon-base-external-dbsource-mysql
Requires-Dist: odoo11-addon-connector
Requires-Dist: odoo11-addon-storage-backend-sftp
Requires-Dist: odoo (<11.1dev,>=11.0a)
Requires-Dist: xmlunittest
